[
  {
    "id": "1",
    "titulo": "Início da Jornada",
    "pergunta": "Qual é o nome da cidade onde o Bob Esponja mora?",
    "opcoes": {
      "A": "Fenda do Biquíni",
      "B": "Pedra do Sol",
      "C": "Cidade das Conchas",
      "D": "Lagoa Goo"
    },
    "respostaCorreta": "A",
    "ingrediente": "Pão"
  },
  {
    "id": "2",
    "titulo": "O Vizinho",
    "pergunta": "Quem mora em uma estátua da Ilha de Páscoa e toca clarinete?",
    "opcoes": {
      "A": "Patrick Estrela",
      "B": "Lula Molusco",
      "C": "Sr. Siriguejo",
      "D": "Gary"
    },
    "respostaCorreta": "B",
    "ingrediente": "Humburguer"
  },
  {
    "id": "3",
    "titulo": "Melhor Amigo",
    "pergunta": "Qual é a cor do Patrick Estrela?",
    "opcoes": {
      "A": "Amarelo",
      "B": "Verde",
      "C": "Rosa",
      "D": "Azul"
    },
    "respostaCorreta": "C",
    "ingrediente": "Queijo"
  },
  {
    "id": "4",
    "titulo": "Trabalho",
    "pergunta": "Qual é o cargo do Bob Esponja no Siri Cascudo?",
    "opcoes": {
      "A": "Gerente",
      "B": "Caixa",
      "C": "Cozinheiro",
      "D": "Limpador de mesas"
    },
    "respostaCorreta": "C",
    "ingrediente": "Alface"
  },
  {
    "id": "5",
    "titulo": "Animais de Estimação",
    "pergunta": "Como o caracol Gary se comunica?",
    "opcoes": {
      "A": "Au au!",
      "B": "Miau!",
      "C": "Piu piu!",
      "D": "Ele fala humano"
    },
    "respostaCorreta": "B",
    "ingrediente": "Tomate"
  },
  {
    "id": "6",
    "titulo": "Artes Marciais",
    "pergunta": "Qual destes personagens é mestre em Caratê e mora numa redoma de vidro?",
    "opcoes": {
      "A": "Plaâncton",
      "B": "Pérola",
      "C": "Sandy Bochechas",
      "D": "Larry, a Lagosta"
    },
    "respostaCorreta": "C",
    "ingrediente": "Cebola"
  },
  {
    "id": "7",
    "titulo": "O Vilão",
    "pergunta": "Qual é o nome do dono do Balde de Lixo que quer roubar a fórmula secreta?",
    "opcoes": {
      "A": "Plâncton",
      "B": "Mancha Negra",
      "C": "Homem Raio",
      "D": "Bolha Suja"
    },
    "respostaCorreta": "A",
    "ingrediente": "Picles"
  },
  {
    "id": "8",
    "titulo": "Dinheiro",
    "pergunta": "O que o Sr. Siriguejo mais ama no mundo?",
    "opcoes": {
      "A": "Hambúrguer de Siri",
      "B": "Dinheiro",
      "C": "Dormir",
      "D": "Pescar"
    },
    "respostaCorreta": "B",
    "ingrediente": "Ketchup"
  },
  {
    "id": "9",
    "titulo": "Transporte",
    "pergunta": "O que o Bob Esponja tenta (e sempre falha) conseguir na escola da Sra. Puff?",
    "opcoes": {
      "A": "Diploma de culinária",
      "B": "Medalha de ouro",
      "C": "Carteira de motorista",
      "D": "Título de melhor aluno"
    },
    "respostaCorreta": "C",
    "ingrediente": "Pão"
  },
  {
    "id": "10",
    "titulo": "Grande Final",
    "pergunta": "Qual é o segredo principal para um Hambúrguer de Siri perfeito?",
    "opcoes": {
      "A": "Muito sal",
      "B": "Fórmula Secreta",
      "C": "Fritar por 2 horas",
      "D": "Pão amanhecido"
    },
    "respostaCorreta": "B",
    "ingrediente": "Lanche Completo"
  }
]